hltv_async_api/__init__.py
hltv_async_api/aiohltv.py
hltv_async_api/unreleased.py
hltv_async_api-0.8.2.dist-info/LICENSE
hltv_async_api-0.8.2.dist-info/METADATA
hltv_async_api-0.8.2.dist-info/WHEEL
hltv_async_api-0.8.2.dist-info/RECORD
