Metadata-Version: 2.1
Name: hltv_async_api
Version: 0.8.2
Summary: An unofficial asynchronous HLTV API Wrapper for Python
Author: Akim Slys
Author-email: akimslys2003@gmail.com
Requires-Python: >=3.9,<4.0
Classifier: License :: OSI Approved :: MIT License
Classifier: Operating System :: OS Independent
Classifier: Programming Language :: Python :: 3
Classifier: Programming Language :: Python :: 3.9
Classifier: Programming Language :: Python :: 3.10
Classifier: Programming Language :: Python :: 3.11
Classifier: Programming Language :: Python :: 3.12
Requires-Dist: aiohttp (>=3.0.1,<4.0.0)
Requires-Dist: beautifulsoup4 (>=4.0.1,<5.0.0)
Requires-Dist: lxml (>=5.0.0,<6.0.0)
Requires-Dist: pytz
Requires-Dist: setuptools
Project-URL: Homepage, https://github.com/akimerslys/aiohltv
Project-URL: Issues, https://github.com/akimerslys/aiohltv/issues
